odoo10_addon_pos_price_to_weight-10.0.1.0.1-py3.8-nspkg.pth
odoo/addons/pos_price_to_weight/README.rst
odoo/addons/pos_price_to_weight/__init__.py
odoo/addons/pos_price_to_weight/__manifest__.py
odoo/addons/pos_price_to_weight/data/barcode_rule.xml
odoo/addons/pos_price_to_weight/demo/product_product.xml
odoo/addons/pos_price_to_weight/i18n/ca.po
odoo/addons/pos_price_to_weight/i18n/es.po
odoo/addons/pos_price_to_weight/i18n/fr.po
odoo/addons/pos_price_to_weight/i18n/it.po
odoo/addons/pos_price_to_weight/i18n/pos_price_to_weight.pot
odoo/addons/pos_price_to_weight/models/__init__.py
odoo/addons/pos_price_to_weight/models/barcode_rule.py
odoo/addons/pos_price_to_weight/static/description/barcode_rule.png
odoo/addons/pos_price_to_weight/static/description/icon.png
odoo/addons/pos_price_to_weight/static/description/pos_test_1.png
odoo/addons/pos_price_to_weight/static/description/pos_test_2.png
odoo/addons/pos_price_to_weight/static/src/js/models.js
odoo/addons/pos_price_to_weight/static/src/js/screens.js
odoo/addons/pos_price_to_weight/static/src/xml/templates.xml
odoo10_addon_pos_price_to_weight-10.0.1.0.1.dist-info/METADATA
odoo10_addon_pos_price_to_weight-10.0.1.0.1.dist-info/WHEEL
odoo10_addon_pos_price_to_weight-10.0.1.0.1.dist-info/namespace_packages.txt
odoo10_addon_pos_price_to_weight-10.0.1.0.1.dist-info/top_level.txt
odoo10_addon_pos_price_to_weight-10.0.1.0.1.dist-info/RECORD
